{"songs": [{"title": "Po T\u0119 Tu (Z\u0142yPrzyk\u0142ad remix)", "album": "RAPERSAMPLER+ (Plus)", "year": "2018-12-07", "lyrics": "[Zwrotka 1]\nTaa, gada\u0142o nam si\u0119 spoko, m\u0142oda pi\u0142a za szybko\nJaka\u015b przygodna znajomo\u015b\u0107, m\u0142oda wys\u0142a\u0142a ten sygna\u0142\nNa imi\u0119 mia\u0142a whatever, gada\u0142em by zabi\u0107 czas\nNic z tego nie b\u0119dzie, to pewex, rozmow\u0119 podtrzymywa\u0142 bas\nDepta\u0142a pety, wybrzmia\u0142y \u015bmiechy\nZgrzyta\u0142y z\u0119by, znika\u0142y \u015bciechy\nWysz\u0142a kt\u00f3r\u0119dy\u015b szuka\u0107 pociechy\nGdzie\u015b mi\u0119dzy kontuarem, parkietem\nSto szturchni\u0119\u0107 p\u00f3\u017aniej i w p\u00f3\u0142 do trzeciej gumy orbit\nWidz\u0119 postaci przy wyj\u015bciu, przy tej kobiecie te dziwne mordy\nBior\u0105 j\u0105 na bok, ale ona stan skupienia: \u017cel\nA ch\u0142opaki amok, omawiaj\u0105 nad ni\u0105 znany cel\nTop jej opada jak Olis w jazzie\nNikt jej nie zdo\u0142a\u0142 przeszkoli\u0107 w imprezie\nPomog\u0119, cho\u0107 mam opory przeze\u0144\nPrzez nich? nie wiem, g\u0142upio, szczerze\nNie znam jej, ale bior\u0119 pod pachy i m\u00f3wi\u0119, stanowczo, raz\nPami\u0119tam miny tych go\u015bci, jakby to by\u0142o wczoraj\n(wczoraj, jakby to by\u0142o wczoraj, wczoraj)\n(wyjd\u0119 z ni\u0105)\n\n[Refren]\nPrzyszed\u0142em po t\u0119 tu dziewczyn\u0119 i wyjd\u0119 z ni\u0105\nPrzyszed\u0142em po t\u0119 tu dziewczyn\u0119\nPrzyszed\u0142em po t\u0119 tu dziewczyn\u0119 i wyjd\u0119 z ni\u0105\nPrzyszed\u0142em po t\u0119 tu dziewczyn\u0119\nDziewczyn\u0119\nDziewczyn\u0119\nDziewczyn\u0119\nDziewczyn\u0119\nDziewczyn\u0119\nDziewczyn\u0119\n\n[Zwrotka 2]\nPodbi\u0142em do kasy z o\u015bmiopakiem papieru Velvet\nPomy\u015bla\u0142a pewnie; trawienie nie jest jego k\u0142opot\u00f3w sednem\nPrzygl\u0105dam si\u0119 kasjerce, czuj\u0119, \u017ce z ni\u0105 b\u0119d\u0119\nMia\u0142a siedemna\u015bcie tego popo\u0142udnia w top markecie\nJa troch\u0119 wi\u0119cej\nMin\u0119\u0142o par\u0119 lat, przesiad\u0142a si\u0119 za biurko\nJa wp\u0142yn\u0105\u0142em na muzyk\u0119 dzi\u0119ki nowym nurtom\nGrono zmieni\u0142o si\u0119 w NK, fejsbuk w insta\nLecz nie uda\u0142o zrobi\u0107 si\u0119 tej relacji re-install\nZbija\u0142em piony na ulicy, jakie\u015b hejty w pismach\nNie mia\u0142em z nikim relacji jak Blake i Krystle\nI zorientowa\u0142em si\u0119 gdzie teraz jest, co robi\nMa ch\u0142opaka, to nie by\u0142 jaki\u015b leszcz bez hobby\nAle gdy stan\u0105\u0142em w drzwiach to ju\u017c bez tanich wyzna\u0144\nWystarczy\u0142o na mnie spojrze\u0107, by przeczyta\u0107 w my\u015blach, \u017ce\nBy przeczyta\u0107 w my\u015blach, \u017ce\n\n[Refren]\nPrzyszed\u0142em po t\u0119 tu dziewczyn\u0119 i wyjd\u0119 z ni\u0105\nPrzyszed\u0142em po t\u0119 tu dziewczyn\u0119\nPrzyszed\u0142em po t\u0119 tu dziewczyn\u0119 i wyjd\u0119 z ni\u0105\nPrzyszed\u0142em po t\u0119 tu dziewczyn\u0119\nPrzyszed\u0142em po t\u0119 dziewczyn\u0119 i wyjd\u0119 z ni\u0105\nPrzyszed\u0142em po t\u0119 dziewczyn\u0119\nPrzyszed\u0142em po t\u0119 dziewczyn\u0119 i wyjd\u0119 z ni\u0105\nPrzyszed\u0142em po t\u0119 dziewczyn\u0119", "image": "https://images.genius.com/ed9c8a783abfd91ab338e5d0389ee41e.1000x1000x1.png"}], "artist": "Ten Typ Mes"}