{"songs": [{"title": "Tylko zwyci\u0119stwo", "album": "25_godzin", "year": "2018-12-14", "lyrics": "[Refren]\nCo? Co? Tylko zwyci\u0119stwo\nCo? Co? Tylko zwyci\u0119stwo\nCo? Co? Tylko zwyci\u0119stwo\nCo? Co?\n\n[Zwrotka 1: Peja]\nLeci dziesi\u0105ty rok \u017cycia bez jakichkolwiek u\u017cywek\nChocia\u017c znam smak pora\u017cki przyzwyczajony do zwyci\u0119stw\nMoje \u017cycie prawdziwe, bo w prawdzie \u017cyje bez obaw\nGdy wybiegam my\u015blami nie musz\u0119 si\u0119 ju\u017c stresowa\u0107\nPrzysz\u0142o\u015b\u0107 \u015bwietlana, bo przesz\u0142o\u015b\u0107 ju\u017c zd\u0105\u017cy\u0142em pochowa\u0107\nTym co przeciwko zapal\u0119 kiedy\u015b znicze na grobach\nKarma rzecz wyj\u0105tkowa nie krzywdz\u0119 ludzi bo po co\nMia\u0142bym do\u015bwiadczy\u0107 b\u00f3lu, kt\u00f3ry przychodzi\u0142 noc\u0105?\nZwyci\u0119stwa s\u0105 moj\u0105 moc\u0105, Rychu troch\u0119 czarodziej\nTe moje kartki z tekstami zmieniam w banknoty na co dzie\u0144\nMotywuje tym m\u0142odzie\u017c, nie obiecuje kokos\u00f3w\nWarto pracowa\u0107 na sukces skuma to kilka os\u00f3b\nReszta w melan\u017cu, ba\u0142agan, \u017cyciowy kibel i tyle\nCo\u015b jak podr\u00f3ba xanaxu doprawiona fentanylem\nPowiesz \u017cycie nie oszcz\u0119dza #Paz de La Huerta\nMam to szcz\u0119\u015bcie by zawrze\u0107 moje zwyci\u0119stwa w wersach\n\n[Zwrotka 2: Eripe]\nK\u0142ad\u0119 si\u0119 spa\u0107 z prze\u015bwiadczeniem \u017ce zrobi\u0142em swoje\nWstaj\u0119 rano z my\u015bl\u0105 ile jeszcze zrobi\u0107 mam\nUbieram \u017cycie w s\u0142owa dzisiaj za\u0142o\u017cy\u0142em koniec\nStania w miejscu by sny nie tylko goni\u0107 w snach\nZiewam na wasze marzenia o fortunie\nUsypiam czujno\u015b\u0107 wrog\u00f3w, potem budz\u0119 ich szacunek\nTe\u017c czasem b\u0142\u0105dz\u0119 chodz\u0119 na o\u015blep jak lunatyk\nPatrz\u0119 na ksi\u0119\u017cyc, \u017cyciem chc\u0119 si\u0119 cieszy\u0107 w pe\u0142ni\nNiebo limitem tylko jak nie umiesz fruwa\u0107 ty\nGwiazdy gasn\u0105 ale nie gin\u0105 legendy\nJa jestem tu po to \u017ceby wygra\u0107\nPobi\u0107 tylko sam si\u0119 ju\u017c mog\u0119 i przez to psychika w bliznach\nI dzika wola walki, unikat pokona kalki\nZabita po\u0142owa rapgry, na bitach im po\u0142am karki\nNiech chyl\u0105 czo\u0142a, a \u0142zy p\u0142yn\u0105 g\u0119sto\nTy wiesz co si\u0119 liczy? Tylko zwyci\u0119stwo\n\n[Bridge: Peja]\nJako zwyci\u0119zca koncentruje si\u0119 na wygranej\nTylko przegrani koncentruj\u0105 sie na zwyci\u0119zcach\nNie patrz na innych sukcesy przecie\u017c nie przyjd\u0105 same\nZr\u00f3b ten wysi\u0142ek, zapracuj oto prosta recepta\n\n[Refren]\nCo? Co? Tylko zwyci\u0119stwo\nCo? Co? Tylko zwyci\u0119stwo\nCo? Co? Tylko zwyci\u0119stwo\nCo? Co?\n\n[Zwrotka 3: Delekta]\nPrzegrani zawsze szukaj\u0105 usprawiedliwie\u0144\nHistorie przegranych zazwyczaj s\u0105 ckliwe\nPrzegrani patrz\u0105 na zwyci\u0119zc\u00f3w wnikliwie\nI bardzo ich wkurwia gdy kto\u015b \u017cyje szcz\u0119\u015bliwie\nLecz ma\u0142o kt\u00f3ry bierze sprawy w swoje r\u0119ce\nBo zawsze czym\u015b innym s\u0105 akurat zaj\u0119te\nTymczasem kto\u015b haruje \u017ceby szlifowa\u0107 sw\u00f3j diament\nBo wie ze tylko dzi\u0119ki pracy ma szanse na zmian\u0119\nZwyci\u0119stwo smakuje najlepiej gdy ma s\u0142ony smak\nZdobyte w pocie czo\u0142a czujesz sie jak Tony Stark\nLudzie pytaj\u0105 jak? Odpowiedz prosta\nTo talent i praca i praca u podstaw\nCi co nie chc\u0105 rusza\u0107 z miejsca\nPozostan\u0105 tam na zawsze maj\u0105c skamienia\u0142e serca\nNa ka\u017cdego przegranego przypada jeden zwyci\u0119zca\nZdecyduj kim chcesz zosta\u0107 to sprawa najwa\u017cniejsza\n\n[Zwrotka 4: Zygson]\nNie sta\u0107 mnie na pora\u017cki, interesuje mnie zwyci\u0119stwo\nWi\u0119c bior\u0119 w swoje d\u0142onie, je\u015bli inni tego nie chc\u0105\nJak Matt Damon, jestem buntownikiem z wyboru\nSkrywam w sobie talent, chocia\u017c nie musz\u0119 stwarza\u0107 pozor\u00f3w\nAsy w r\u0119kawie, jak Negreanu, zaczn\u0105 liczy\u0107 si\u0119 z przegran\u0105\nBo tylko konsekwentni tu zostan\u0105, z wygran\u0105\nRazem z ekip\u0105, wsp\u00f3lnie lecimy na podb\u00f3j\nTwardy grunt, no bo pod nogami podium\nNiech nikt Ci tu nie wm\u00f3wi, \u017ce nie znaczysz nic\nToksyczne towarzystwo zmie\u0144, zacznij na przek\u00f3r \u017cy\u0107\nStopie\u0144 po stopniu, jestem \u017cycia liderem\nOdgradzam teren, obieram kurs, staje za sterem\n\u0141atwo nie przychodzi nic, gdy upadasz, wstajesz\nGdy chc\u0105 ci co\u015b narzuci\u0107, ty miej swoje zdanie\nMatk\u0105 sukcesu jest cierpliwo\u015b\u0107, to wiem na pewno\nWi\u0119c Ty te\u017c powtarzaj na g\u0142os TYLKO ZWYCI\u0118STWO!\n\n[Refren]\nCo? Co? Tylko zwyci\u0119stwo\nCo? Co? Tylko zwyci\u0119stwo\nCo? Co? Tylko zwyci\u0119stwo\nCo? Co?\n\n[Zwrotka 5: Kobra]\nSzczylu, zastanawiasz si\u0119 dlaczego mam Nike na butach\nAll I do is Win i zn\u00f3w wydzwaniam Monik\u0119 na fiuta\nM\u00f3j kole\u017cka tutaj opierdala Jazz jak Utah\nM\u00f3wi, \u017ce wygra\u0142 weekend znowu mu si\u0119 zgadza utarg\nKa\u017cdy dzie\u0144 to urodziny\nSuka wyskakuje z tortu kurwa ka\u017cdy dzie\u0144 to urodziny\nOne to gwiazdy dlatego nosz\u0119 sneakersy i pisz\u0119 wersy\nSLU Gang to zwyci\u0119zcy, merci!\nCo jest s\u0119py, zn\u00f3w g\u0142odne na cudzy sukces\nAle takie wersy jak ty to pisa\u0142em kurwa w podstaw\u00f3wce\nOto czempion! S\u0142ysza\u0142em ju\u017c na porod\u00f3wce\nCzarny ko\u0144 nie tylko na tej polo bluzce\nSuki z ma\u0142ych miast ich sen o Warszawie ja \u015bni\u0142em sen o wiktorii\nPotem mia\u0142em Wiktori\u0119 na jawie\nHonor, duma, przyja\u017a\u0144, odwaga i m\u0119stwo\nTylko zwyci\u0119stwo!\n\n[Zwrotka 6: EsZet]\nWchodz\u0119 do gry, zazwyczaj w pierwszej pi\u0105tce\nI cho\u0107 mo\u017cesz mnie nie zna\u0107, to sobie nie\u017ale szponc\u0119\nTylko zwyci\u0119stwo, nikt tu nie gra by przegra\u0107\nWed\u0142ug zasad, po swojemu, co\u015b ci nie gra to \u017cegnam\nZiomu\u015b, trzeba trzyma\u0107 fason i wygra\u0107 to s\u0142usznie\nA jak przegra\u0107 to z klas\u0105, z tym bywa to r\u00f3\u017cnie\nSukces ma wiele imion, w mig rozkmi\u0144 to wreszcie\nMoja \u015blubna obr\u0105czka jest jak mistrzowski pier\u015bcie\u0144\nJak przegrywasz to nie czekaj a\u017c si\u0119 zmieni tura\nNie mo\u017cesz wygra\u0107, to do nich do\u0142\u0105cz jak Kevin Durant\nNie no, bez jaj, cho\u0107 styl masz znamienity\nTo jakby\u015b wali\u0142 konia pod stos z\u0142otych p\u0142yt za same featy\nMia\u0142em nie szydzi\u0107, ale zn\u00f3w to robi\u0119\nPATO PATO to dynastia kr\u00f3l\u00f3w jak Tudorowie\nZiomu\u015b, Queen mo\u017ce \u015bpiewa\u0107 z nami kim jeste\u015bmy\nB\u0119dziemy walczy\u0107 do ko\u0144ca, oto w\u0142a\u015bnie kim jeste\u015bmy\n(przyjacielu)\n\n[Refren]\nCo? Co? Tylko zwyci\u0119stwo\nCo? Co? Tylko zwyci\u0119stwo\nCo? Co? Tylko zwyci\u0119stwo\nCo? Co?", "image": "https://images.genius.com/d5eeeea15496bd61821ef85a98ee7a0b.862x862x1.jpg"}], "artist": "Peja"}