{"songs": [{"title": "BANGERMAJSTER", "album": "MOONLIGHT", "year": "2014-09-27", "lyrics": "{INTRO}\nEj (oh), yeah (aha)\nR do E do T do O suko (pow pow pow pow)\n\n{REFREN}\nBANGERMAJSTER,zabijam gr\u0119\nJak J\u00e4germeister wale cie w \u0142eb (tak jest)\nCzy masz charakter by ruszy\u0107 mnie?\nJa to BANGERMAJSTER\n\n{ZWROTKA 1}\nBANGERMAJSTER,zabijam gr\u0119\nDziwki chc\u0105 mie\u0107 swag, czuj\u0119 si\u0119 jak swag bo chc\u0105 mnie\nDziwki lubi\u0105 swag, dziwki lubi\u0105 hajs, dziwki lubi\u0105 \u0107pa\u0107\nMog\u0105 da\u0107, mog\u0105 spa\u0107 z tob\u0105 jak grasz rap\nJa gram rap ja gram trap i kurwy mam dziwki\nStoi jedna obok drugiej w tekstach  jak o przecinki\nJeste\u015b jak Lil' kim, nie dajesz dupy okej\nCiekawe co o wszystkim powiedzia\u0142 by christopher\nReTo \u015bmiga na bitach i m\u00f3wi\u0105 wje\u017cd\u017ca nie\u017ale\nWe\u017a si\u0119 zmywaj bo przypa\u0142 kiedy ten BANGER kre\u015bl\u0119\nI biegn\u0119 po penge i wiem \u017ce dobiegn\u0119\nJak jebn\u0119, zetn\u0119 z nich reszt\u0119 na to starczy refren\n\n{REFREN}x2\nBANGERMAJSTER,zabijam gr\u0119\nJak J\u00e4germeister wale cie w \u0142eb\nCzy masz charakter by ruszy\u0107 mnie\nJa to BANGERMAJSTER\n\n[BRIDGE]\nBANGERMAJSTER (oh)\nBANGERMAJSTER (what)x3\nBANGERMAJSTER (skrrt)x2\nBANGERMAJSTER x2\n\n{ZWROTKA 2}\nCome back \u0142aki tu cisn\u0105, \u0142akiem od \u0142ak\u00f3w\nI to jest \u015bmieszne, dlatego czasem dosy\u0107 mam rapu\nBo to dzieciaku jest oporowo tandetne\nTypy z zezem no nie wierze chc\u0105 tu przej\u0105\u0107 gr\u0119\nPrzez to spojrzenie nie widz\u0105 lepszych mam przej\u0105\u0107 si\u0119?\nWidz\u0105 ja\u0142e ego frajerom to m\u00f3wi\u0105 won st\u0105d\nPanny na was lec\u0105 tylko wtedy jak si\u0119 potkn\u0105\nPrzyszed\u0142em tu po penge tym cipom zamykam drzwi\nNie my\u015bl\u0105 o napadzie za klamk\u0119 nie z\u0142apie nikt\nMoney on my mind bitch, money on my mind\nWszyscy chc\u0105 mie\u0107 hajs, tylko ja go b\u0119d\u0119 mia\u0142\nLepiej nie ruchaj fan\u00f3w, lepiej ich przesta\u0144 jeba\u0107\nBo kt\u00f3rego\u015b dnia fan wyrucha ciebie schwesta ewa\n\n{REFREN}x2\nBANGERMAJSTER,zabijam gr\u0119\nJak J\u00e4germeister wale cie w \u0142eb\nCzy masz charakter by ruszy\u0107 mnie\nJa to BANGERMAJSTER", "image": "https://images.genius.com/397e073eba061edeb650b6bae97e863c.400x400x1.png"}], "artist": "ReTo"}