{"songs": [{"title": "Z\u0142o\u015b\u0107", "album": "7", "year": "2006-02-24", "lyrics": "[Intro: O.S.T.R.]\nGdzie, gdzie ty jeste\u015b, gdzie ty jeste\u015b, gdzie?\nGdzie ty jeste\u015b, gdzie ty jeste\u015b, gdzie?\n\n[Zwrotka 1: O.S.T.R.]\nJest takie miejsce tam gdzie stres jest panem\nTam gdzie magnum 44 ogniem przestrze\u0144 daje\nOszcz\u0119d\u017a, przerwij manewr, dosy\u0107 z ulicy tajemnic\nKrew, walki ps\u00f3w plus niewolnicy agresji\nPrzewodniczy nam presti\u017c, pi\u0119\u015bci\nLub szybkie nogi do ucieczki\nLepszy mi\u0119kki grunt, bunt i \u015blepa mi\u0142o\u015b\u0107 do pieni\u0119dzy\nWierny Bogu dzi\u015b zaliczany jest do wrog\u00f3w\nPom\u00f3\u017c komu\u015b a stracisz z\u0119by\nBuja to skuma ka\u017cdy hajs raczy dragi alko i od chuja panny\nKluby, kt\u00f3rych d\u0142ugi biznes to kurwy i clowny\nSpakujmy ten \u015bwiat i za burt\u0119 wywalmy\nPrzesta\u0144, bo to ten \u015bwiat nas wywali z mieszka\u0144\nWydani przez strach 22.05 Interwencja\nTu jest ta zguba, przemoc, stres i prewencja\nPies, co szczeg\u00f3\u0142y spami\u0119ta\nWiesz to regu\u0142y w mendach tkwi\u0105\nPa\u0142a, but, pa\u0142a, brzuch, but i dzwon\nJak mam tu spotka\u0107 z\u0142o to nie dzi\u015b?\nKurwy won, p\u0142onie li\u015b\u0107, poczuj to cannabis\nCzyli joint sw\u0105d skunka, bo nie znam si\u0119 na klamkach\nMam m\u00f3zg i pi\u0119\u015bci plus \u0142y\u017cw\u0119 na najkach\nUczysz si\u0119 na pora\u017ckach osiedli jak te\nNa peryferiach miasta adrenalina wzrasta\nTy masz tak, ja mam tak\n\n[Refren: O.S.T.R.]\nCo s\u0142ycha\u0107, co, co s\u0142ycha\u0107 ziom\nCo s\u0142ycha\u0107, co, co s\u0142ycha\u0107 ziom\nCo s\u0142ycha\u0107, co, co s\u0142ycha\u0107 ziom\nCo s\u0142ycha\u0107, co, to z\u0142o\u015b\u0107\n\n[Zwrotka 2: O.S.T.R.]\nNied\u0142ugo \u015bwiat ju\u017c nas nie zechce\nKto\u015b odpali bomb\u0119 potem zewrze\nPo co pali\u0107 ziomy swoje miejsce\nBitomany ci\u0105gle maj\u0105 wej\u015bcie dla zakochanych\nCwanym daj\u0105c w ge\u015bcie moc\nNiespo\u017cytej w\u0142adzy azyl i agresje koks\nSatelit\u0119 wra\u017ce\u0144 w bran\u017cy jak i w seksie\nZajrzyj za tym sens jest, nie, ziomek bzdura\nTu jest dla ciebie zaw\u00f3d znaczy cz\u0142owiek figurant\nCokolwiek nie wsk\u00f3rasz za wiele\nMarzy\u0107 o w\u0142adzy znaczy by\u0107 ruchomym celem, kapish?\nI tak kto\u015b inny zyska na twojej biografii\nOd policyjnej mafii skorumpowanych ps\u00f3w\nDo tych, co bluzgali stoj\u0105c nad twoj\u0105 trumn\u0105, trudno\nKolejny temat na bestseller\nTak mia\u0142o by\u0107, zabi\u0142a ciebie \u017cona z przyjacielem\nCzy warto? ka\u017cdy wybiera sw\u00f3j hardcore\nTen dar, co prowadzi nas ku zbawiennemu \u015bwiatu\nNiewinnemu da gn\u00f3j a winnemu hajsu\nNie wiesz, czemu tak tu\nLos nami gardzi bez \u015bwiadk\u00f3w\nCo noc\u0105 poszukiwani sprawcy\nOszukani zbawcy wersu \u015bwiata zdobywcy\nFortuna ponad prawem nier\u00f3wnym dla wszystkich\n\n[Scratche]\nDo\u015b\u0107 tych sentymentalnych piosenek\n\n[Refren: O.S.T.R.]\nCo s\u0142ycha\u0107, co, co s\u0142ycha\u0107 ziom\nCo s\u0142ycha\u0107, co, co s\u0142ycha\u0107 ziom\nCo s\u0142ycha\u0107, co, co s\u0142ycha\u0107 ziom\nCo s\u0142ycha\u0107, co, to z\u0142o\u015b\u0107\n\n[Scratche x4]\nDo\u015b\u0107 tych sentymentalnych piosenek\n\n[Outro: Kochan]\nPam pam pam pam pam pam pa\nSzacunek dla wszystkich prawdziwych kurwa, DJ-e\nDla wszystkich, ode mnie, od Kochana\nAdam, twoje zdrowie, mam nadziej\u0119 \u017ce to nagrywasz eej\n\u017be zawsze b\u0119dziesz o nas pami\u0119ta\u0142, eej\nI \u017ce to wszystko zostanie mi\u0119dzy nami, eej\n\n[Tekst i adnotacje na Rap Genius Polska]", "image": "https://images.genius.com/b36e32227ba79737a1394750f62539a5.410x410x1.jpg"}], "artist": "O.S.T.R."}