{"songs": [{"title": "Ka\u017cdy ch\u0142opaczyna z blok\u00f3w", "album": "Dow\u00f3d rzeczowy nr 2", "year": "2011-01-01", "lyrics": "[Refren]\nMarzy o tym ka\u017cdy ch\u0142opaczyna z blok\u00f3w\nMie\u0107 mieszkanie, kozacki samoch\u00f3d\nHajsu pe\u0142na kiesze\u0144, w pliku nowa seria\nSztuka u\u015bmiechni\u0119ta, na jej d\u0142oni bi\u017cuteria\n\n[Zwrotka 1]\n25 lat wstecz, z tornistrami id\u0105 ch\u0142opcy\nMama m\u00f3wi \"nie bierz s\u0142odyczy od obcych\"\nZ workiem na kapcie mijam matematyce\nDo dzi\u015b pami\u0119tam zgrzyt jej paznokci o tablice\nDawno temu i nie prawda, czasy podstaw\u00f3wki\nChcieli\u015bmy wrzuci\u0107 \u017cab\u0119 do sokowir\u00f3wki\nMieli\u015bmy co\u015b z szara\u0144czy\nCzasy kiedy w sklepach nie by\u0142o pomara\u0144czy\nFrajd\u0105 by\u0142o przejechanie si\u0119 taks\u00f3wk\u0105\nBia\u0142ostocki projekt suko, nie wakacje w Acapulko\nZ orbity marze\u0144 prosto o ziemi\u0119 po sprawie\nDzi\u015b \u017cycie koncentruje si\u0119 w osiedlowym pubie\nTyle pijanych dusz, tuu\nEgoizm do szcz\u0119\u015bcia klucz, ju\u017c\nNie jeden ch\u0142opaczyna jedyne co mo\u017ce\nTo po pijaku terroryzowa\u0107 bankomat no\u017cem\nInni \u017cycie za pysk trzymaj\u0105 kr\u00f3tko\nPieprzy\u0107 marny los pod go\u0142\u0105 \u017car\u00f3wk\u0105\n\u017badne g\u0142\u00f3d i ch\u0142\u00f3d i nie pij\u0105 na smutno\nGorza\u0142\u0119 gol\u0105, id\u0105 z dol\u0105 na solo\n\n[Refren]\n\n[Zwrotka 2]\nBezsporny fakt, tu nie lubi si\u0119 policji\nZa to przywi\u0105zanie do tradycji\nChocia\u017c bida czasem piszczy, twarze dumne\nCi\u0119\u017cko tu \u017cy\u0107, ale szkoda umrze\u0107\nNa balkonach suszy si\u0119 pranie\nSznur ludzi idzie na niedzielne kazanie\nKochane s\u0105siadki okupuj\u0105 \u0142awki\nJeszcze wczoraj m\u0142ode, jutro gro\u017c\u0105 im gerbera papki\nCzasami spe\u0142nia si\u0119 tu polskie marzenie\nMie\u0107 przynajmniej na w\u0142asno\u015b\u0107 m1\nNie ma tu miejsca na zaniechania grzech\nNa ludzi kt\u00f3rzy maj\u0105 w \u017cy\u0142ach wod\u0119 a nie krew\nS\u0142ysz\u0119, kto\u015b komu\u015b zn\u00f3w ubli\u017ca\nStara babina przed sob\u0105 robi znak krzy\u017ca\nTu tylko bloki, nigdy tego nie zrozumiesz\nPi\u0107 piwo na melan\u017cu to jak pierdoli\u0107 w gumie\n\n[Refren]\n\n[Zwrotka 3]\nJedni w konfesjonale daj\u0105 upust swoim smutkom\nInni spowiadaj\u0105 si\u0119 ospa\u0142ym prostytutkom\nKto\u015b straszy dup\u0119, \u017ce skoczy z mostu\nMo\u017cesz si\u0119 \u015bmia\u0107, tak jest po prostu\nJak wredne skrzypienie, noc\u0105 zak\u0142\u00f3ca cisz\u0119\nNa wietrze pusta hu\u015btawka si\u0119 ko\u0142ysze\nNie ma jak betonu dotyk\nKiedy umr\u0119 rozrzu\u0107 nad osiedlem moje prochy\nOgl\u0105danie witryn w sklepach czasem jest tu wszystkim\nNa wystawach plastikowe anorektyczki\nBrakuje do pierwszego, nic jako\u015b b\u0119dzie\nW pi\u0105tek ju\u017c si\u0119 m\u00f3wi o kolejnym weekendzie\nCa\u0142y czas \u017cycie w jak\u0105\u015b akcj\u0119 ci\u0119 pakuje\nTu w wielu spojrzeniach, t\u0119sknota za rozumem\nTy tego nie wiesz, lecz cz\u0119\u015b\u0107 z nich ju\u017c wie\nJak si\u0119 je jajko Faberge\n\n[Refren]", "image": "https://images.genius.com/3ce5bf730648e798c45c3d1ff251e898.709x709x1.jpg"}], "artist": "PiH"}