{"songs": [{"title": "Runa", "album": "W drodze po szcz\u0119\u015bcie EP", "year": "2018-02-23", "lyrics": "[Zwrotka 1]\nPono\u0107 dzisiaj nie ma magii\nTylko interes dw\u00f3ch stron\nWielbi\u0105 du\u017ce nomina\u0142y\nA nie znaleziony grosz\nLubi\u0105 szybkie auta, szybkie laski\nS\u0142odkie k\u0142amstwa, koks\nIntelekt ich nie nadaje si\u0119 nawet do mycia r\u0105k\nKumpel m\u00f3wi\u0142 \"mi\u0142o\u015b\u0107 \u017cycia\", \u017ce ju\u017c nie ma takich dzi\u015b\nFigura, kasa obycia z g\u00f3ry skazany na flirt\nKas\u0119 wydawa\u0142 po\u017cycza\u0142, utopi\u0142 by siebie w tym\nW ko\u0144cu wpad\u0142a czwarty miesi\u0105c\nTylko szkoda, \u017ce nie z nim\n\nM\u00f3j przyjaciel drugi raz odwo\u0142a\u0142 \u015blub\nJak tu wierzy\u0107 w wielk\u0105 mi\u0142o\u015b\u0107\nPrzysi\u0119gi s\u0142owa po gr\u00f3b\nB\u00f3g obdarzy\u0142 j\u0105 urod\u0105\nAle po\u017ca\u0142owa\u0142 cn\u00f3t\nWszyscy \u015bwi\u0119ci, cho\u0107 nie trzyma si\u0119 im aureola g\u0142\u00f3w!\n\n[Refren x2]\nM\u00f3wi\u0119 co widz\u0119, co, co widz\u0119, co widz\u0119, wiem wiem co widz\u0119, mowie co widz\u0119, co, co widz\u0119, po-podejd\u017a bli\u017cej, wiem wiem co widz\u0119\n\n[Zwrotka 2]\nKiedy s\u0142o\u0144ce mam w gar\u015bci\nPo co mi gwiazdy na jedn\u0105 noc\nPowiedzia\u0142 mi kuzyn, nie znaj\u0105c prawdy\nO swojej drugiej po\u0142owie, przez kolejn\u0105 noc\nWierzy\u0142, \u017ce wr\u00f3ci, wszystko jej da\u0142by\nTylko by sp\u0119dzi\u0107 z ni\u0105 nami\u0119tn\u0105 noc\nRobi\u0142a to z ka\u017cdym, tylko nie z nim\nA mia\u0142a by\u0107 jego, recept\u0105 na z\u0142o\nPono\u0107 nie ma mi\u0142o\u015bci\nLiczy si\u0119 tylko interes dw\u00f3ch stron\nZdrady, rozwody, romanse, w pracy\nDroga do s\u0142awy, przez \u0142\u00f3\u017cko, na tron\nTemu ci\u0105gn\u0119\u0142am, a z tym si\u0119 wali\u0142am\nDzieciaki to ch\u0142on\u0105, jak najlepsze show\nChodzimy jak ludzie, my\u015blimy jak ma\u0142py\nB\u0142\u0105d w demografii, miejskie zoo\nM\u00f3wi\u0105 nie ma magii, tylko kalkulator cyfr\n\nBrat m\u00f3j wyjecha\u0142 do Anglii\n\u017bonie wysy\u0142a\u0142 wci\u0105\u017c kwit\nB\u0142aga\u0142a, \u017ce t\u0119skni za nim\n\u017be nie ma go tyle dni\nWr\u00f3ci\u0142 wcze\u015bniej z zaskoczenia\nObcy typ otworzy\u0142 drzwi\n\nM\u00f3j przyjaciel drugi raz odwo\u0142a\u0142 \u015blub\nJak tu wierzy\u0107 w wielk\u0105 mi\u0142o\u015b\u0107\nW przysi\u0119gi, s\u0142owa po gr\u00f3b\nB\u00f3g obdarzy\u0142 j\u0105 urod\u0105\nAle po\u017ca\u0142owa\u0142 cn\u00f3t\nWszyscy \u015bwi\u0119ci, cho\u0107 nie trzyma si\u0119 im aureola g\u0142\u00f3w!\n\n[Refren x2]\nM\u00f3wi\u0119 co widz\u0119, co, co widz\u0119, co widz\u0119, wiem wiem co widz\u0119, mowie co widz\u0119, co, co widz\u0119, po-podejd\u017a bli\u017cej, wiem wiem co widz\u0119", "image": "https://images.genius.com/865ea0794e15535c8d8b0ef7412c57d0.500x500x1.png"}], "artist": "O.S.T.R."}