{"songs": [{"title": "Niespe\u0142nione Obietnice", "album": "Droga", "year": "2009-04-15", "lyrics": "[Refren: Wilku]\nNiespe\u0142nione obietnice\n\n[Zwrotka 1: Wilku]\nNa ulicy s\u0142owo dro\u017csze od pieni\u0119dzy\nBiznes jest biznes, ka\u017cdy za czym\u015b p\u0119dzi\nJa nie zbiednieje, lamus du\u017co wi\u0119cej straci\nKiedy\u015b si\u0119 odbije wr\u00f3ci jak na tacy ziom\nKto daje plam\u0119 musi po\u017cegna\u0107 szacunek\nBy\u0142o takich paru obrali z\u0142y kierunek\nNiby tacy twardzi, niby znali si\u0119 na rzeczy\nDzi\u015b ju\u017c nie ma ich w\u015br\u00f3d nas, nikt nie zaprzeczy\n\n[Refren: Wilku 2x]\n\n[Zwrotka 2: Bilon]\nNie raz s\u0142ysza\u0142em kiedy\u015b, rap szczery elo ziom\nDzi\u015b to stek bzdur na si\u0142\u0119 lany gniot\nTo zwyk\u0142y kmiot, jak zawieje zmienia tor\nTif to i stad bij strza\u0142\u0119 poszed\u0142 w\u0105t\nNiestety boli niespe\u0142niona obietnica\nNie\u0142atwo jest wybacza\u0107 gdy ranne s\u0105 uczucia\nFarmazon\u00f3w s\u0142ucha\u0107 mam kolejny raz? (nie!)\nKiedy\u015b wierzy\u0142em w to....\n\n[Refren: Wilku 2x]\n\n[Zwrotka 3: Wilku]\nPomy\u015bl co chcesz powiedzie\u0107 zanim zaczniesz si\u0119 j\u0105ka\u0107\nUnikasz ludzi kt\u00f3rych za nic nie chcesz spotka\u0107\nTwoje gwarancje wielu bra\u0142o za pewnik\nCi co oszukuj\u0105 samych siebie s\u0105 na prawd\u0119 biedni\nNie czujesz winy gdy w \u017cy\u0142ach syf si\u0119 toczy\nMy\u015blisz, \u017ce jeste\u015b inny? Synu otw\u00f3rz oczy\nNarkotyki i alkohol to codzienno\u015b\u0107 chleb powszedni\nW domu chlew w bani m\u0119tlik, a w duszy \u015bmietnik\n\n[Refren: Wilku] 2x\n\n[Zwrotka 4: Bilon]\nNie popisa\u0142e\u015b si\u0119 prezydenciku \u015bmieszny\nZe swoj\u0105 siostr\u0105 Jarkiem dla kraju niebezpieczny\nMasakra miazga, zlansowany m\u00f3zg odpu\u015b\u0107 ju\u017c wa\u015b\u0107\nSprz\u0105tnij po sobie gruz, z mordy cholewa co robi\u0105 obietnice\nPierdole to, co pierdoli jaki\u015b ch\u0142ystek\nZaliczy\u0142 mielizn\u0119 niech zostanie tam i ski\u015bnie\nTo jest to co my\u015bl\u0119 oczywi\u015bcie oczywiste\n\n[Refren: Wilku 2x]\n\n[Zwrotka 5: Wilku]\nNie jeden si\u0119 zarzeka\u0142 ze nie sprzeda si\u0119 za ma\u0142o\nParu niepotrzebnie za to w og\u00f3le si\u0119 bra\u0142o\nTylko kilku od pocz\u0105tku gra w otwarte karty\nA nie wielu ma to w sercu dla was ziomy farcik\nNajwa\u017cniejszy portfel, wiem z czego\u015b \u017cy\u0107 trzeba\nW si\u00f3dmym niebie zapomnia\u0142e\u015b o korzeniach stop\nNie ma tu miejsca dla padaki i mas\u00f3wki\n\u015amiej\u0105 z Ciebie nawet dzieciaki z podstaw\u00f3wki\n\n[Refren: Wilku 2x]\n\n[Zwrotka 6: Bilon]\nLecz sam nie jestem \u015bwi\u0119ty bo w \u017cyciu r\u00f3\u017cnie jest\nCzasami zawiod\u0142em chocia\u017c stara\u0142em si\u0119 wiem\nNa dobrych ch\u0119ciach zbudowane piek\u0142o\nNie raz na pewno skoczy\u0142o w g\u00f3r\u0119 t\u0119tno\nPewne jest jedno s\u0142owa obraca\u0107 w czyn\nNie ma co obiecywa\u0107 pustym gadaniem zby\u0107\nWzbudzi\u0107 nadzieje a potem z tego kpi\u0107\nTak si\u0119 nie robi jak z lud\u017ami chce sie \u017cy\u0107, Elo\n[Tekst i adnotacje na Rap Genius Polska]", "image": "https://images.genius.com/4f9893fade69848e8855783c23f5d89e.450x450x1.png"}], "artist": "Hemp Gru"}