{"songs": [{"title": "Nie wierz\u0119 w \u017cycie wieczne", "album": "Poezja", "year": null, "lyrics": "Moment\u00f3w\nTalia kart do gry, dom, cichy jak wszech\u015bwiat\nTalia klepsydry, mi\u0142o\u015b\u0107, obj\u0119to\u015b\u0107 ziarenka\nPrzysz\u0142o\u015b\u0107 i przesz\u0142o\u015b\u0107, zwyci\u0119stwo i kl\u0119ska\nMoment\u00f3w\nReszta to pech\nReszta to piach\nTeraz to puch\nTeraz to pch\u0142a\nMoment\u00f3w\nSw\u0119dzenie duszy\nOpuszki duszy\nUda i uszy\nDucha i duszy\nMoment\u00f3w\n\n\n\nNie wierz\u0119 w \u017cycie wieczne\nMoment\u00f3w\nJest we mnie tysi\u0105ce \u015bmierci\nCzas ju\u017c nie p\u0142ynie lecz wierci\nSi\u0119 przy pami\u0119ci w \u017ca\u0142obie\nK\u0142\u0119by dymu, \u015bwiat\u0142a zgaszone\nMemento\n\nZnajduj\u0119\nCzarny w\u0142os pogubiony w sk\u0142\u0119bionej ko\u0142drze\nW\u0142os Ariadny, w\u0142os syreny, w\u0142osy nimfy morskiej\nW kt\u00f3rych trzymam d\u0142o\u0144 duszy, lepiej tak ni\u017c w og\u00f3le\n\nNa moment\nWszystko by\u0142o dobrze\nZa moment\nWszystko b\u0119dzie dobrze\nPo-wr\u00f3c\u0119\n\nZnam szybkie \u015bmierci moment\u00f3w\nKocham ich kr\u00f3tkie \u017cycia\nBarwne wybuchy puch\u015bwiat\u00f3w\nCiche t\u0105pni\u0119cia z(ach!)wytu\n\nI jak Nabokov\nJestem\nLepidopterologiem", "image": "https://images.genius.com/c19b569ed8fa05626ac8ae8e741b9204.182x182x1.jpg"}], "artist": "Bisz"}