{"songs": [{"title": "Nie\u015bmiertelny", "album": "HALFLAJF", "year": "2016-12-09", "lyrics": "[Zwrotka 1 ]\n2K16 pi\u0119tna\u015bcie feat\u00f3w im da\u0142em ju\u017c jest maj dopiero\nWpad\u0142o ponad 100k bez cd gdzie twoje auto Venom?\nPo o mi ono ja ci\u0105gle chlej\u0119 dzie\u0144 w dzie\u0144 jezd\u017c\u0119\nUberem wsz\u0119dzie wystrzelony nieraz jakbym by\u0142 Angry Birdem\nIle b\u0119d\u0119 mia\u0142 lat, jak zgin\u0119, mi wszystko jedno\nMam 32, si\u0142ownia pokazuje 23; mirror error\nDefinicja hedonizmu i etosu pracy\n\u015amigaj ze mn\u0105 w pizdu nie wiadomo w jak\u0105 ci\u0119 stron\u0119 spaczy\nR&B wraca na pe\u0142nej u Fa\u0142ka\nNawet jak utopimy na was mordy to b\u0119d\u0119 to bangla\u0142\nNie wydajemy g\u00f3wna nawet jak \u015bmierdzi hajsem\nPospolite gusta dla nas na dnie horyzontalnie\nHajs na tjubie te\u017c leci fakt\nAle my\u015blisz, \u017ce J Cole'a rusza, ile lajk\u00f3w ma Iggy czy Fetty Wap?\nA king in his own mind, m\u00f3j prime synu\nWci\u0105\u017c trwa, flow V, jestem nie\u015bmiertelny\n\n[Refren]\nNie boj\u0119 si\u0119 budzi\u0107 i tak nie \u015bpi\u0119 kiedy \u015bni\u0119\nKiedy zgin\u0119 dla tysi\u0119cy b\u0119d\u0119 nie\u015bmiertelny wiem\nNie zabiega\u0142em o to nie, chcia\u0142em tylko hajsu dla siebie\nAle nie skurwi\u0142em si\u0119 dla niego a i tak go mam b\u0119d\u0119 nie\u015bmiertelny\nB\u0119d\u0119 nie\u015bmiertelny x8\n\n[Zwrotka 2]\nBliskim m\u00f3wi\u0142em, \u017ce jak po\u017cegnam korpo for life pokryj\u0119 cia\u0142o ca\u0142e swoje w tatua\u017cach\nDla mojej mamy to po\u015bwi\u0119cenie, jakby kto\u015b po mnie zmywa\u0142 tu krew z o\u0142tarza\nTo mo\u017ce przera\u017ca\u0107\nWiem, \u017ce my\u015bli to samo, co koledzy z bran\u017cy, gdy wchodz\u0119 na feat im \"Tomek, tylko nie przesadzaj\"\nAle ja lec\u0119, jakbym wskoczy\u0142 na grzbiet pegaza\nTe stare czy nowe koty ju\u017c w og\u00f3le nie mog\u0105 tu ze mn\u0105 gada\u0107\nNadaj\u0119 na innych falach\nTych, co budz\u0105 si\u0119 pod ziemi\u0105, a ko\u0144cz\u0105 na himalajach\nFlota jak Vasco da Gama, ona p\u00f3\u0142naga\nOdpala szampany, ja kody na god mode do rana\nKurwa tak gram, wpieprz\u0119 to na instagram\nNie s\u0142ysza\u0142a\u015b KLAUD N9JN, przestaw si\u0119 jak anagram\nTo s\u0105 Legendarne flowsy, jak Jay nie licz\u0119 CD, odk\u0105d wiem\n\u017be kurwa z samych moich feat\u00f3w, synu, zrobi\u0142bym pi\u0119\u0107\nMusz\u0119 zajeba\u0107 testament, bo kiedy\nZgin\u0119 kurwa sprzedamy diament i b\u0119d\u0119 nie\u015bmiertelny\n\n[Refren]\nNie boj\u0119 si\u0119 budzi\u0107 i tak nie \u015bpi\u0119 kiedy \u015bni\u0119\nKiedy zgin\u0119 dla tysi\u0119cy b\u0119d\u0119 nie\u015bmiertelny wiem\nNie zabiega\u0142em o to nie, chcia\u0142em tylko hajsu dla siebie\nAle nie skurwi\u0142em si\u0119 dla niego a i tak go mam b\u0119d\u0119 nie\u015bmiertelny\nB\u0119d\u0119 nie\u015bmiertelny x8\n\n[Tekst i adnotacje na Rap Genius Polska]", "image": "https://images.genius.com/4c62771a7e62a2025d868df59b089b97.960x960x1.jpg"}], "artist": "VNM"}