{"songs": [{"title": "Do nast\u0119pnego", "album": "\u0179r\u00f3d\u0142o LP", "year": "2016-05-13", "lyrics": "[Intro: Kaz Ba\u0142agane & Belmondo]\n2016 - G, Ba\u0142agane (najaaaak) czeka\u0142e\u015b na to\nHehe, mordziaty, mordziaty...\n\n[Refren: Kaz Ba\u0142agane & Belmondo]\nMordziaty, mordziaty, mordziaty, mordziaty, mordziaty\nCzy to hip-hop'y, czy to ju\u017c rapy?\nMOBBYN, mordziaty tymczasem\nKto\u015b dzwoni to papier, si\u0119 nie \u017cegnamy\nDo zobaczenia niebawem\nMordziaty, mordziaty, mordziaty tymczasem\nMordziaty, mordziaty, mordziaty, mordziaty, mordziaty\nCzy to hip-hop'y, czy to ju\u017c rapy?\nMOBBYN, mordziaty tymczasem\nKto\u015b dzwoni to papier, si\u0119 nie \u017cegnamy\nDo zobaczenia niebawem\nMordziaty, mordziaty, mordziaty tymczasem\n\n[Zwrotka 1: Kaz Ba\u0142agane]\nWpierdalam futomaki, tw\u00f3j rap stuleja i tw\u00f3j sk\u0142ad \u0142oniaki\nGdzie po feat'a mi podbijasz tutaj z g\u00f3wnem jakim\u015b?\nNie jestem m\u0142odym wilkiem, tylko kr\u00f3lem stada\nWpierdalam si\u0119 do rap-gry, nikt mnie tutaj nie wprowadza\u0142\nKto Ci da\u0142 pierwszy w Polsce rap?\nKto powiedzia\u0142 \u017ceby tu nie kocha\u0107 szmat?\nLeci Pac, wbita na dach, polo bluza, Ty masz bluz\u0119 gap\nYoung OG jak wap, st\u00f3j a nie flak, nikogo nie by\u0142o tutaj jak my\nBe do Gie i m\u0142ody G - nowe rapsy, w TV ogl\u0105dasz \u017cyd\u00f3w i fakty\n\n[Bridge: Belmondo]\nG, Ba\u0142agane! Ty w TV ogl\u0105dasz kabaret, ty czytasz kaba\u0142\u0119\nZamykasz cha\u0142ap\u0119, twoi ludzie kasztany\nId\u0119 robi\u0107 sobie cash \u2013 money, nie kasz\u0119 mann\u0119\nMoi ludzie to klasyk! Do zobaczenia mordziaty tymczasem\n\n[Refren: Kaz Ba\u0142agane & Belmondo]\nMordziaty, mordziaty, mordziaty, mordziaty, mordziaty\nCzy to hip-hop'y, czy to ju\u017c rapy?\nMOBBYN, mordziaty tymczasem\nKto\u015b dzwoni to papier, si\u0119 nie \u017cegnamy\nDo zobaczenia niebawem\nMordziaty, mordziaty, mordziaty tymczasem\nMordziaty, mordziaty, mordziaty, mordziaty, mordziaty\nCzy to hip-hop'y, czy to ju\u017c rapy?\nMOBBYN, mordziaty tymczasem\nKto\u015b dzwoni to papier, si\u0119 nie \u017cegnamy\nDo zobaczenia niebawem\nMordziaty, mordziaty, mordziaty tymczasem\n\n[Zwrotka 2: Kaz Ba\u0142agane]\nNawet kiedy nie robi\u0142em rapu, to puszcza\u0142em p\u0142yty\nNawet kiedy nie wiedzia\u0142e\u015b o tym buja\u0142e\u015b si\u0119 przy tym\nZnowu w studiu robi\u0142em tutaj siano\nZanim u\u017cywali drum rolli tam w pizdu na po\u0142udniu\nNie jestem swager typu jeba\u0107 bied\u0119\nPierwsze rzeczy wypada\u0142y z rozjebanych 501\nDzi\u015b mam wiedze, dzi\u015b mam wszystko nowe\nDzi\u015b mnie wszystko jebie\nBe do Gie i kolega, do us\u0142yszenia na nowym CD\n\n[Bridge: Belmondo]\nG, Ba\u0142agane! Ty w TV ogl\u0105dasz kabaret, ty czytasz kaba\u0142\u0119\nZamykasz cha\u0142ap\u0119, twoi ludzie kasztany\nId\u0119 robi\u0107 sobie cash \u2013 money, nie kasz\u0119 mann\u0119\nMoi ludzie to klasyk! Do zobaczenia mordziaty tymczasem\n\n[Refren: Kaz Ba\u0142agane & Belmondo]\nMordziaty, mordziaty, mordziaty, mordziaty, mordziaty\nCzy to hip-hop'y, czy to ju\u017c rapy?\nMOBBYN, mordziaty tymczasem\nKto\u015b dzwoni to papier, si\u0119 nie \u017cegnamy\nDo zobaczenia niebawem\nMordziaty, mordziaty, mordziaty tymczasem\nMordziaty, mordziaty, mordziaty, mordziaty, mordziaty\nCzy to hip-hop'y, czy to ju\u017c rapy?\nMOBBYN, mordziaty tymczasem\nKto\u015b dzwoni to papier, si\u0119 nie \u017cegnamy\nDo zobaczenia niebawem\nMordziaty, mordziaty, mordziaty tymczasem", "image": "https://images.genius.com/21ced7c20097e7cf66bf8eea0603a940.1000x1000x1.jpg"}], "artist": "Kaz Ba\u0142agane"}